LICENSE
MANIFEST.in
README.rst
setup.py
CrawlerCodePythonTools_Gui.egg-info/PKG-INFO
CrawlerCodePythonTools_Gui.egg-info/SOURCES.txt
CrawlerCodePythonTools_Gui.egg-info/dependency_links.txt
CrawlerCodePythonTools_Gui.egg-info/requires.txt
CrawlerCodePythonTools_Gui.egg-info/top_level.txt
pythontools/gui/__init__.py
pythontools/gui/app.py
pythontools/gui/button.py
pythontools/gui/contextmenu.py
pythontools/gui/edits.py
pythontools/gui/gui.py
pythontools/gui/label.py
pythontools/gui/listwidget.py
pythontools/gui/menubar.py
pythontools/gui/object.py
pythontools/gui/tray.py
pythontools/gui/window.py